README.md
setup.cfg
setup.py
rfpyutils/__init__.py
rfpyutils.egg-info/PKG-INFO
rfpyutils.egg-info/SOURCES.txt
rfpyutils.egg-info/dependency_links.txt
rfpyutils.egg-info/top_level.txt
rfpyutils/array/__init__.py
rfpyutils/array/rf_utils_array.py
rfpyutils/built/__init__.py
rfpyutils/built/rf_utils_built.py
rfpyutils/log/__init__.py
rfpyutils/log/rf_utils_logger.py
rfpyutils/str/__init__.py
rfpyutils/str/rf_utils_str.py