Metadata-Version: 2.1
Name: rfpyutils
Version: 0.0.6
Summary: Library utilities for python
Home-page: https://github.com/diegorufe/rfpyutils
Author: Diego Ruiz
Author-email: diegorufe@gmail.com
License: UNKNOWN
Platform: UNKNOWN
Classifier: Programming Language :: Python :: 3
Classifier: Operating System :: OS Independent
Requires-Python: >=3.8
